aws_client_wrapper/__init__.py
aws_client_wrapper/CacheService/__init__.py
aws_client_wrapper/CacheService/redisWrapper.py
aws_client_wrapper/CacheService/utils.py
aws_client_wrapper/cloudfront.py
aws_client_wrapper/cloudfront_storage.py
aws_client_wrapper/configure.py
aws_client_wrapper/connection.py
aws_client_wrapper/constants.py
aws_client_wrapper/s3.py
aws_client_wrapper/s3_storage.py
aws_client_wrapper/stats.py
aws_client_wrapper/utils.py
aws_client_wrapper-1.0.4.dist-info/METADATA
aws_client_wrapper-1.0.4.dist-info/WHEEL
aws_client_wrapper-1.0.4.dist-info/RECORD
