Metadata-Version: 2.1
Name: aws-client-wrapper
Version: 1.0.4
Summary: A versatile Python library for seamless access to Amazon S3 and CloudFront using ARN role-based authorization. This wrapper, built atop Boto3, enables easy integration with Python 3.11 and facilitates AWS resource access from within Google Cloud Platform environments.
Author: anilmaurya-bst
Author-email: anilkumar.maurya@bluestacks.com
Requires-Python: >=3.11,<4.0
Classifier: Programming Language :: Python :: 3
Classifier: Programming Language :: Python :: 3.11
Classifier: Programming Language :: Python :: 3.12
Requires-Dist: boto3 (>=1.34.69,<2.0.0)
Requires-Dist: redis (>=5.0.3,<6.0.0)
Requires-Dist: requests (>=2.31.0,<3.0.0)
